SaebHelloWorld/__init__.py
SaebHelloWorld/hello.py
SaebHelloWorld-0.0.3.dist-info/METADATA
SaebHelloWorld-0.0.3.dist-info/WHEEL
SaebHelloWorld-0.0.3.dist-info/top_level.txt
SaebHelloWorld-0.0.3.dist-info/RECORD
