Metadata-Version: 2.1
Name: SaebHelloWorld
Version: 0.0.3
Summary: Test uploading a package.
Home-page: UNKNOWN
Author: Saeb
Author-email: <saeb.ragani@gmail.com>
License: UNKNOWN
Keywords: test
Platform: UNKNOWN
Classifier: Development Status :: 1 - Planning
Classifier: Intended Audience :: Developers
Classifier: Programming Language :: Python :: 3
Classifier: Operating System :: Unix
Classifier: Operating System :: MacOS :: MacOS X
Classifier: Operating System :: Microsoft :: Windows
